dev_bot_cli/__init__.py
dev_bot_cli/__main__.py
dev_bot_cli/command/__init__.py
dev_bot_cli/command/prune_remote.py
dev_bot_cli-0.1.0.dist-info/WHEEL
dev_bot_cli-0.1.0.dist-info/entry_points.txt
dev_bot_cli-0.1.0.dist-info/METADATA
dev_bot_cli-0.1.0.dist-info/RECORD
