Metadata-Version: 2.1
Name: dev-bot-cli
Version: 0.1.0
Summary: 
Author: Cristiam Sosa
Author-email: cristiam.sosa@innocv.com
Requires-Python: >=3.9,<4.0
Classifier: Programming Language :: Python :: 3
Classifier: Programming Language :: Python :: 3.9
Classifier: Programming Language :: Python :: 3.10
Classifier: Programming Language :: Python :: 3.11
Requires-Dist: click (>=8.1.3,<9.0.0)
Requires-Dist: gitpython (>=3.1.31,<4.0.0)
